{
	"parent": "midnight:recipes/root",
	"rewards": {
		"recipes": [
			"midnight:shadowroot_door",
			"midnight:shadowroot_slab",
			"midnight:shadowroot_stairs",
			"midnight:shadowroot_trapdoor",
			"midnight:shadowroot_chest",
			"midnight:shadowroot_crafting_table",
			"midnight:shadowroot_button",
			"midnight:shadowroot_pressure_plate"
		]
	},
	"criteria": {
		"requirement_1": {
			"trigger": "minecraft:inventory_changed",
			"conditions": {
				"items": [{
					"item": "midnight:shadowroot_planks"
				}]
			}
		}
	}
}
