{
	"parent": "midnight:recipes/root",
	"rewards": {
		"recipes": [
			"midnight:dead_wood_door",
			"midnight:dead_wood_slab",
			"midnight:dead_wood_stairs",
			"midnight:dead_wood_trapdoor",
			"midnight:dead_wood_chest",
			"midnight:dead_wood_crafting_table",
			"midnight:dead_wood_button",
			"midnight:dead_wood_pressure_plate"
		]
	},
	"criteria": {
		"requirement_1": {
			"trigger": "minecraft:inventory_changed",
			"conditions": {
				"items": [{
					"item": "midnight:dead_wood_planks"
				}]
			}
		}
	}
}
